package/__init__.py
package/karachi_ml_flood_detection (1).py
karachifloodmlmodel-0.1.0.dist-info/METADATA
karachifloodmlmodel-0.1.0.dist-info/WHEEL
karachifloodmlmodel-0.1.0.dist-info/top_level.txt
karachifloodmlmodel-0.1.0.dist-info/RECORD
