Metadata-Version: 2.4
Name: karachiFloodMLModel
Version: 0.1.0
Summary: Short description of your package
Author: EshanGillani
Requires-Python: >=3.8
